{
    "": "170.39", 
    "sector": "Industrials", 
    "Date_Time": "2018-07-19 00:00:30.350937", 
    "Operating_Margin": 0.13716, 
    "url": "http://finance.yahoo.com/quote/CAT?p=CAT", 
    "ROA": 0.05345, 
    "industry": "Farm & Construction Equipment", 
    "target_est": 170.39, 
    "state": "IL", 
    "EPS": 3.7, 
    "beta": 1.528658, 
    "Total_Debt": 35318001664, 
    "Total_Cash": 7033999872, 
    "Earnings_Date": "2018-07-30", 
    "Current_Price": 141.12, 
    "Free_Cash_Flow": 2005374976, 
    "ticker": "CAT", 
    "Gross_Profits": 12035000000
}